pianistpy/__init__.py
pianistpy/df_class.py
pianistpy-0.0.1.dist-info/METADATA
pianistpy-0.0.1.dist-info/WHEEL
pianistpy-0.0.1.dist-info/RECORD
